setup.py
babel_util/__init__.py
babel_util.egg-info/PKG-INFO
babel_util.egg-info/SOURCES.txt
babel_util.egg-info/dependency_links.txt
babel_util.egg-info/requires.txt
babel_util.egg-info/top_level.txt
babel_util/parsers/__init__.py
babel_util/parsers/aminer.py
babel_util/parsers/aminer_test.py
babel_util/parsers/cocite.py
babel_util/parsers/tree.py
babel_util/parsers/tree_test.py
babel_util/recommenders/__init__.py
babel_util/recommenders/bibcouple.py
babel_util/recommenders/cocitation.py
babel_util/recommenders/ef.py
babel_util/recommenders/ef_nx.py