Metadata-Version: 1.1
Name: babel-util
Version: 1.0.1
Summary: Utilities to support the babel platform
Home-page: https://github.com/jevinw/rec_utilities
Author: The Babel Development Team
Author-email: babel_platform_discuss@googlegroups.com
License: GNU Affero General Public License
Platform: UNKNOWN
Classifier: Development Status :: 3 - Alpha
Classifier: Intended Audience :: Science/Research
Classifier: Topic :: Scientific/Engineering :: Information Analysis
Classifier: License :: OSI Approved :: GNU Affero General Public License v3 or later (AGPLv3+)
Classifier: Programming Language :: Python :: 2
Classifier: Programming Language :: Python :: 2.6
Classifier: Programming Language :: Python :: 2.7
